sqlalchemy_csv_normalise/__init__.py
sqlalchemy_csv_normalise-0.1.2.dist-info/AUTHORS.rst
sqlalchemy_csv_normalise-0.1.2.dist-info/LICENSE
sqlalchemy_csv_normalise-0.1.2.dist-info/METADATA
sqlalchemy_csv_normalise-0.1.2.dist-info/WHEEL
sqlalchemy_csv_normalise-0.1.2.dist-info/top_level.txt
sqlalchemy_csv_normalise-0.1.2.dist-info/RECORD
