Metadata-Version: 2.1
Name: sqlalchemy-csv-normalise
Version: 0.1.2
Summary: SQLAlchemy utilities for normalising / denormalising table data, useful for CSV
Home-page: https://github.com/mohawk2/sqlalchemy-csv-normalise
Author: Ed J
Author-email: mohawk2@users.noreply.github.com
License: MIT license
Keywords: sqlalchemy-csv-normalise
Platform: UNKNOWN
Classifier: Development Status :: 2 - Pre-Alpha
Classifier: Intended Audience :: Developers
Classifier: License :: OSI Approved :: MIT License
Classifier: Natural Language :: English
Classifier: Programming Language :: Python :: 3
Classifier: Programming Language :: Python :: 3.5
Classifier: Programming Language :: Python :: 3.6
Classifier: Programming Language :: Python :: 3.7
Classifier: Programming Language :: Python :: 3.8
Requires-Python: >=3.5
Requires-Dist: SQLAlchemy (>=1.3.8)
Requires-Dist: python-dateutil (>=2.8.1)
